stereo3d/__init__.py
stereo3d/stereocalibration.py
stereo3d/stereocapture/__init__.py
stereo3d/stereocapture/cvcapture.py
stereo3d/stereocapture/cvimagecapture.py
stereo3d/stereocapture/cvimagefoldercapture.py
stereo3d/stereocapture/iccapture.py
stereo3d/stereocapture/pyloncapture.py
stereo3d/stereocapture/stereocapturecvdual.py
stereo3d/stereocapture/stereocapturecvsplit.py
stereo3d/stereocapture/stereocapturepylon.py
stereo3d/stereocapture/stereocapturevrep.py
stereo3d/stereocapture/tis.py
stereo3d/stereocapture/vrepcapture.py
stereo3d/stereocapture/coppeliasim/__init__.py
stereo3d/stereocapture/coppeliasim/sim.py
stereo3d/stereocapture/coppeliasim/simConst.py
stereo3d/stereocapture/coppeliasim/data/MacOS/remoteApi.dylib
stereo3d/stereocapture/coppeliasim/data/Windows/remoteApi.dll
stereo3d-0.0.8.dist-info/METADATA
stereo3d-0.0.8.dist-info/WHEEL
stereo3d-0.0.8.dist-info/top_level.txt
stereo3d-0.0.8.dist-info/RECORD
