Metadata-Version: 2.1
Name: stereo3d
Version: 0.0.8
Summary: Generating 3D data from stereo images.
Home-page: https://github.com/i3drobotics/Stereo3D
Author: Ben Knight
Author-email: bknight@i3drobotics.com
License: UNKNOWN
Platform: UNKNOWN
Classifier: Programming Language :: Python :: 3
Classifier: License :: OSI Approved :: MIT License
Classifier: Operating System :: OS Independent
Requires-Python: >=3.6
Requires-Dist: opencv-python
Requires-Dist: pymsgbox
Requires-Dist: pypylon
Requires-Dist: pyntcloud
Requires-Dist: numpy ; python_version == "3.5"
Requires-Dist: numpy (==1.19.3) ; python_version > "3.5"
